lap_data/__init__.py
lap_data/_meta.py
lap_data/_version.py
lap_data/lcmodel.py
lap_data-4.3.36.dist-info/LICENSE
lap_data-4.3.36.dist-info/METADATA
lap_data-4.3.36.dist-info/WHEEL
lap_data-4.3.36.dist-info/top_level.txt
lap_data-4.3.36.dist-info/RECORD
