Metadata-Version: 2.1
Name: lap_data
Version: 4.3.36
Summary: Laser Aided Profiler Data Access Library
Author-email: Peter Demján <peter.demjan@gmail.com>
License: GNU General Public License v3 (GPLv3)
Project-URL: homepage, https://github.com/demjanp/lap_data
Keywords: database,graph
Classifier: Development Status :: 5 - Production/Stable
Classifier: Intended Audience :: Science/Research
Classifier: Topic :: Database
Classifier: License :: OSI Approved :: GNU General Public License v3 (GPLv3)
Classifier: Programming Language :: Python :: 3.10
Classifier: Operating System :: Microsoft :: Windows :: Windows 10
Requires-Python: <4,>=3.10
License-File: LICENSE
Requires-Dist: deposit-gui<2,>=1.6.36
